{
  "name" : "Village Form",
  "uuid" : "0b2685fd-a39f-4ec7-afcb-158c63ffda7d",
  "formType" : "IndividualProfile",
  "formElementGroups" : [ {
    "uuid" : "1344dead-dd38-4eb3-9f7c-100b31ce2ec6",
    "name" : "Village Basic Information",
    "displayOrder" : 1.0,
    "formElements" : [ {
      "name" : "Account",
      "uuid" : "aead4a04-c6dd-423a-abf6-524bd06d52de",
      "keyValues" : [ ],
      "concept" : {
        "name" : "Account  name",
        "uuid" : "2978117c-a297-4171-99c6-23c3522ca0f8",
        "dataType" : "Text",
        "answers" : [ ],
        "active" : true
      },
      "displayOrder" : 1.0,
      "type" : "SingleSelect",
      "mandatory" : true
    }, {
      "name" : "State",
      "uuid" : "ad25a175-7ada-4560-b222-d14c66345813",
      "keyValues" : [ ],
      "concept" : {
        "name" : "State",
        "uuid" : "fdcb1ae2-505d-4784-993f-1de9d5e2ba60",
        "dataType" : "Location",
        "answers" : [ ],
        "active" : true,
        "keyValues" : [ {
          "key" : "isWithinCatchment",
          "value" : true
        }, {
          "key" : "lowestAddressLevelTypeUUIDs",
          "value" : [ "3410e7a2-cefe-4fc7-94b4-6631656c548c" ]
        }, {
          "key" : "highestAddressLevelTypeUUID",
          "value" : "fda77dde-6346-47b9-84e0-25e7f171f55a"
        } ]
      },
      "displayOrder" : 2.0,
      "type" : "SingleSelect",
      "mandatory" : true
    }, {
      "name" : "District",
      "uuid" : "12605b7a-bb93-4976-8014-98699dd310f4",
      "keyValues" : [ ],
      "concept" : {
        "name" : "District",
        "uuid" : "667a4546-f08e-434b-9f4c-60e285061313",
        "dataType" : "Location",
        "answers" : [ ],
        "active" : true,
        "keyValues" : [ {
          "key" : "isWithinCatchment",
          "value" : true
        }, {
          "key" : "lowestAddressLevelTypeUUIDs",
          "value" : [ "3410e7a2-cefe-4fc7-94b4-6631656c548c" ]
        } ]
      },
      "displayOrder" : 3.0,
      "type" : "SingleSelect",
      "mandatory" : true
    }, {
      "name" : "Block",
      "uuid" : "d98fb891-a0bc-4d4b-b8b6-52d93f4d8377",
      "keyValues" : [ ],
      "concept" : {
        "name" : "Block Code",
        "uuid" : "115d2ce2-e810-4745-bf9b-d4ac7ffe6565",
        "dataType" : "Numeric",
        "answers" : [ ],
        "active" : true
      },
      "displayOrder" : 4.0,
      "type" : "SingleSelect",
      "mandatory" : true
    }, {
      "name" : "Village",
      "uuid" : "b2af2a9f-76e4-4cc7-bde6-0ce897c96e6d",
      "keyValues" : [ ],
      "concept" : {
        "name" : "Distribution Village",
        "uuid" : "4e0bf8ca-62b1-4fa6-8df2-d264379d2df2",
        "dataType" : "Text",
        "answers" : [ ],
        "active" : true,
        "keyValues" : [ ]
      },
      "displayOrder" : 5.0,
      "type" : "SingleSelect",
      "mandatory" : true
    } ],
    "display" : "Village Basic Information",
    "timed" : false
  }, {
    "uuid" : "1c2bad98-2d39-4cb5-9f4b-27d2d2dbbd43",
    "name" : "Village Detail Information",
    "displayOrder" : 2.0,
    "formElements" : [ ],
    "display" : "Village Detail Information",
    "timed" : false
  } ],
  "decisionRule" : "",
  "visitScheduleRule" : "",
  "validationRule" : "",
  "checklistsRule" : "",
  "decisionConcepts" : [ ]
}